pyphenix/__init__.py
pyphenix/_reader.py
pyphenix/_version.py
pyphenix/_widget.py
pyphenix/_writer.py
pyphenix/napari.yaml
pyphenix-0.1.5.dist-info/licenses/LICENSE
pyphenix-0.1.5.dist-info/METADATA
pyphenix-0.1.5.dist-info/WHEEL
pyphenix-0.1.5.dist-info/entry_points.txt
pyphenix-0.1.5.dist-info/top_level.txt
pyphenix-0.1.5.dist-info/RECORD
