Metadata-Version: 2.4
Name: pyphenix
Version: 0.1.5
Summary: A data loader and widget to visualize high-dimensional data collected on the Opera Phenix
Author: Max Ferrin
Author-email: ferrin@calicolabs.com
License: 
Project-URL: Bug Tracker, https://github.com/ferrinm/pyphenix/issues
Project-URL: Documentation, https://github.com/ferrinm/pyphenix#README.md
Project-URL: Source Code, https://github.com/ferrinm/pyphenix
Project-URL: User Support, https://github.com/ferrinm/pyphenix/issues
Classifier: Development Status :: 2 - Pre-Alpha
Classifier: Framework :: napari
Classifier: Intended Audience :: Developers
Classifier: License :: OSI Approved :: GNU General Public License v3 (GPLv3)
Classifier: Operating System :: OS Independent
Classifier: Programming Language :: Python
Classifier: Programming Language :: Python :: 3
Classifier: Programming Language :: Python :: 3 :: Only
Classifier: Programming Language :: Python :: 3.10
Classifier: Programming Language :: Python :: 3.11
Classifier: Programming Language :: Python :: 3.12
Classifier: Programming Language :: Python :: 3.13
Classifier: Topic :: Scientific/Engineering :: Image Processing
Requires-Python: >=3.10
License-File: LICENSE
Requires-Dist: numpy
Requires-Dist: magicgui
Requires-Dist: qtpy
Requires-Dist: scikit-image
Requires-Dist: jupyter>=1.1.1
Provides-Extra: all
Requires-Dist: napari[all]; extra == "all"
Dynamic: license-file
